README.md
setup.py
ypy/__init__.py
ypy/bsub.py
ypy/fs.py
ypy/iter.py
ypy/memo.py
ypy/pretty.py
ypy.egg-info/PKG-INFO
ypy.egg-info/SOURCES.txt
ypy.egg-info/dependency_links.txt
ypy.egg-info/not-zip-safe
ypy.egg-info/top_level.txt