Metadata-Version: 1.0
Name: ypy
Version: 0.1
Summary: Python utility functions used in yakirr repos
Home-page: http://github.com/yakirr/ypy
Author: Yakir Reshef
Author-email: yakir@seas.harvard.edu
License: MIT
Platform: UNKNOWN
